sesocial/__init__.py
sesocial/se.py
SE_social-1.2.3.dist-info/LICENSE
SE_social-1.2.3.dist-info/METADATA
SE_social-1.2.3.dist-info/WHEEL
SE_social-1.2.3.dist-info/top_level.txt
SE_social-1.2.3.dist-info/RECORD
