Metadata-Version: 2.1
Name: SE-social
Version: 1.2.3
Summary: A python library for verifying and generating swedish social security numbers
Home-page: https://github.com/WaldemarBjornstrom/SEsocial
Author: WaldemarBjornstrom
Author-email: Waldemar.bjornstrom@unfnorrbotten.se
License: MIT
Platform: UNKNOWN
Classifier: License :: OSI Approved :: MIT License
Classifier: Development Status :: 5 - Production/Stable
Classifier: Intended Audience :: Developers
Classifier: Programming Language :: Python :: 3
Classifier: Programming Language :: Python :: 3.6
Classifier: Programming Language :: Python :: 3.7
Classifier: Programming Language :: Python :: 3.8
Classifier: Programming Language :: Python :: 3.9
License-File: LICENSE
